Workbook

Sheet Dashboard
B1: 💰 PERSONAL FINANCE DASHBOARD
B2: Everything below updates automatically from the Transactions sheet
B4: Period: | C4: YTD (This Year) | F4: =TEXT($N$4,"mmm d, yyyy")&" — "&TEXT($N$5,"mmm d, yyyy") | K4: Annual Interest: | L4: 0.05 | N4: =IFERROR(INDEX(Settings!$I$7:$I$34,MATCH($C$4,Settings!$H$7:$H$34,0)),DATE(YEAR(TODAY()),1,1))
N5: =IFERROR(INDEX(Settings!$J$7:$J$34,MATCH($C$4,Settings!$H$7:$H$34,0)),EOMONTH(TODAY(),0))
B6: 💵 INCOME | E6: 💸 EXPENSES | H6: 🏦 NET SAVINGS (w/ Int) | K6: 📈 SAVINGS RATE | N6: =IFERROR(INDEX(Settings!$K$7:$K$34,MATCH($C$4,Settings!$H$7:$H$34,0)),MONTH(TODAY()))
B7: =SUMIFS(Transactions!$E:$E,Transactions!$D:$D,"Income",Transactions!$A:$A,">="&$N$4,Transactions!$A:$A,"<="&$N$5) | E7: =SUMIFS(Transactions!$E:$E,Transactions!$D:$D,"Expense",Transactions!$A:$A,">="&$N$4,Transactions!$A:$A,"<="&$N$5) | H7: =($B$7-$E$7) * (1 + ($L$4 / 12) * $N$6) | K7: =IFERROR(($B$7-$E$7)/$B$7,0)
B8: ="₱"&TEXT(IFERROR($B$7/$N$6,0),"#,##0")&" avg / month" | E8: ="₱"&TEXT(IFERROR($E$7/$N$6,0),"#,##0")&" avg / month" | H8: ="₱"&TEXT(IFERROR($H$7/$N$6,0),"#,##0")&" avg / month" | K8: ="of ₱"&TEXT($B$7,"#,##0")&" earned"
B10: 🎯 Budget vs Actual
B11: Category | C11: Monthly Budget | D11: Period Budget | E11: Actual | F11: Remaining | G11: % Used | H11: Status
B12: =Settings!$B$11 | C12: =IFERROR(Settings!$D$11,0) | D12: =$C12*$N$6 | E12: =SUMIFS(Transactions!$E:$E,Transactions!$C:$C,$B12,Transactions!$D:$D,"Expense",Transactions!$A:$A,">="&$N$4,Transactions!$A:$A,"<="&$N$5) | F12: =$D12-$E12 | G12: =IFERROR($E12/$D12,0) | H12: =IF($G12>1,"🔴 Over budget",IF($G12>=0.85,"🟡 Getting close","🟢 On track"))
B13: =Settings!$B$12 | C13: =IFERROR(Settings!$D$12,0) | D13: =$C13*$N$6 | E13: =SUMIFS(Transactions!$E:$E,Transactions!$C:$C,$B13,Transactions!$D:$D,"Expense",Transactions!$A:$A,">="&$N$4,Transactions!$A:$A,"<="&$N$5) | F13: =$D13-$E13 | G13: =IFERROR($E13/$D13,0) | H13: =IF($G13>1,"🔴 Over budget",IF($G13>=0.85,"🟡 Getting close","🟢 On track"))
B14: =Settings!$B$13 | C14: =IFERROR(Settings!$D$13,0) | D14: =$C14*$N$6 | E14: =SUMIFS(Transactions!$E:$E,Transactions!$C:$C,$B14,Transactions!$D:$D,"Expense",Transactions!$A:$A,">="&$N$4,Transactions!$A:$A,"<="&$N$5) | F14: =$D14-$E14 | G14: =IFERROR($E14/$D14,0) | H14: =IF($G14>1,"🔴 Over budget",IF($G14>=0.85,"🟡 Getting close","🟢 On track"))
B15: =Settings!$B$14 | C15: =IFERROR(Settings!$D$14,0) | D15: =$C15*$N$6 | E15: =SUMIFS(Transactions!$E:$E,Transactions!$C:$C,$B15,Transactions!$D:$D,"Expense",Transactions!$A:$A,">="&$N$4,Transactions!$A:$A,"<="&$N$5) | F15: =$D15-$E15 | G15: =IFERROR($E15/$D15,0) | H15: =IF($G15>1,"🔴 Over budget",IF($G15>=0.85,"🟡 Getting close","🟢 On track"))
B16: =Settings!$B$15 | C16: =IFERROR(Settings!$D$15,0) | D16: =$C16*$N$6 | E16: =SUMIFS(Transactions!$E:$E,Transactions!$C:$C,$B16,Transactions!$D:$D,"Expense",Transactions!$A:$A,">="&$N$4,Transactions!$A:$A,"<="&$N$5) | F16: =$D16-$E16 | G16: =IFERROR($E16/$D16,0) | H16: =IF($G16>1,"🔴 Over budget",IF($G16>=0.85,"🟡 Getting close","🟢 On track"))
B17: =Settings!$B$16 | C17: =IFERROR(Settings!$D$16,0) | D17: =$C17*$N$6 | E17: =SUMIFS(Transactions!$E:$E,Transactions!$C:$C,$B17,Transactions!$D:$D,"Expense",Transactions!$A:$A,">="&$N$4,Transactions!$A:$A,"<="&$N$5) | F17: =$D17-$E17 | G17: =IFERROR($E17/$D17,0) | H17: =IF($G17>1,"🔴 Over budget",IF($G17>=0.85,"🟡 Getting close","🟢 On track"))
B18: =Settings!$B$17 | C18: =IFERROR(Settings!$D$17,0) | D18: =$C18*$N$6 | E18: =SUMIFS(Transactions!$E:$E,Transactions!$C:$C,$B18,Transactions!$D:$D,"Expense",Transactions!$A:$A,">="&$N$4,Transactions!$A:$A,"<="&$N$5) | F18: =$D18-$E18 | G18: =IFERROR($E18/$D18,0) | H18: =IF($G18>1,"🔴 Over budget",IF($G18>=0.85,"🟡 Getting close","🟢 On track"))
B19: =Settings!$B$18 | C19: =IFERROR(Settings!$D$18,0) | D19: =$C19*$N$6 | E19: =SUMIFS(Transactions!$E:$E,Transactions!$C:$C,$B19,Transactions!$D:$D,"Expense",Transactions!$A:$A,">="&$N$4,Transactions!$A:$A,"<="&$N$5) | F19: =$D19-$E19 | G19: =IFERROR($E19/$D19,0) | H19: =IF($G19>1,"🔴 Over budget",IF($G19>=0.85,"🟡 Getting close","🟢 On track"))
B20: =Settings!$B$19 | C20: =IFERROR(Settings!$D$19,0) | D20: =$C20*$N$6 | E20: =SUMIFS(Transactions!$E:$E,Transactions!$C:$C,$B20,Transactions!$D:$D,"Expense",Transactions!$A:$A,">="&$N$4,Transactions!$A:$A,"<="&$N$5) | F20: =$D20-$E20 | G20: =IFERROR($E20/$D20,0) | H20: =IF($G20>1,"🔴 Over budget",IF($G20>=0.85,"🟡 Getting close","🟢 On track"))
B21: =Settings!$B$20 | C21: =IFERROR(Settings!$D$20,0) | D21: =$C21*$N$6 | E21: =SUMIFS(Transactions!$E:$E,Transactions!$C:$C,$B21,Transactions!$D:$D,"Expense",Transactions!$A:$A,">="&$N$4,Transactions!$A:$A,"<="&$N$5) | F21: =$D21-$E21 | G21: =IFERROR($E21/$D21,0) | H21: =IF($G21>1,"🔴 Over budget",IF($G21>=0.85,"🟡 Getting close","🟢 On track"))
B22: =Settings!$B$21 | C22: =IFERROR(Settings!$D$21,0) | D22: =$C22*$N$6 | E22: =SUMIFS(Transactions!$E:$E,Transactions!$C:$C,$B22,Transactions!$D:$D,"Expense",Transactions!$A:$A,">="&$N$4,Transactions!$A:$A,"<="&$N$5) | F22: =$D22-$E22 | G22: =IFERROR($E22/$D22,0) | H22: =IF($G22>1,"🔴 Over budget",IF($G22>=0.85,"🟡 Getting close","🟢 On track"))
B23: TOTAL | C23: =SUM(C12:C22) | D23: =SUM(D12:D22) | E23: =SUM(E12:E22) | F23: =$D23-$E23 | G23: =IFERROR($E23/$D23,0)
B25: 📈 Cash Flow — Last 12 Months
B26: Month | C26: Income | D26: Expenses | E26: Net
B27: =TEXT(EOMONTH(TODAY(),-11),"mmm yy") | C27: =SUMIFS(Transactions!$E:$E,Transactions!$D:$D,"Income",Transactions!$A:$A,">="&(EOMONTH(TODAY(),-12)+1),Transactions!$A:$A,"<="&EOMONTH(TODAY(),-11)) | D27: =SUMIFS(Transactions!$E:$E,Transactions!$D:$D,"Expense",Transactions!$A:$A,">="&(EOMONTH(TODAY(),-12)+1),Transactions!$A:$A,"<="&EOMONTH(TODAY(),-11)) | E27: =$C27-$D27
B28: =TEXT(EOMONTH(TODAY(),-10),"mmm yy") | C28: =SUMIFS(Transactions!$E:$E,Transactions!$D:$D,"Income",Transactions!$A:$A,">="&(EOMONTH(TODAY(),-11)+1),Transactions!$A:$A,"<="&EOMONTH(TODAY(),-10)) | D28: =SUMIFS(Transactions!$E:$E,Transactions!$D:$D,"Expense",Transactions!$A:$A,">="&(EOMONTH(TODAY(),-11)+1),Transactions!$A:$A,"<="&EOMONTH(TODAY(),-10)) | E28: =$C28-$D28
B29: =TEXT(EOMONTH(TODAY(),-9),"mmm yy") | C29: =SUMIFS(Transactions!$E:$E,Transactions!$D:$D,"Income",Transactions!$A:$A,">="&(EOMONTH(TODAY(),-10)+1),Transactions!$A:$A,"<="&EOMONTH(TODAY(),-9)) | D29: =SUMIFS(Transactions!$E:$E,Transactions!$D:$D,"Expense",Transactions!$A:$A,">="&(EOMONTH(TODAY(),-10)+1),Transactions!$A:$A,"<="&EOMONTH(TODAY(),-9)) | E29: =$C29-$D29
B30: =TEXT(EOMONTH(TODAY(),-8),"mmm yy") | C30: =SUMIFS(Transactions!$E:$E,Transactions!$D:$D,"Income",Transactions!$A:$A,">="&(EOMONTH(TODAY(),-9)+1),Transactions!$A:$A,"<="&EOMONTH(TODAY(),-8)) | D30: =SUMIFS(Transactions!$E:$E,Transactions!$D:$D,"Expense",Transactions!$A:$A,">="&(EOMONTH(TODAY(),-9)+1),Transactions!$A:$A,"<="&EOMONTH(TODAY(),-8)) | E30: =$C30-$D30
B31: =TEXT(EOMONTH(TODAY(),-7),"mmm yy") | C31: =SUMIFS(Transactions!$E:$E,Transactions!$D:$D,"Income",Transactions!$A:$A,">="&(EOMONTH(TODAY(),-8)+1),Transactions!$A:$A,"<="&EOMONTH(TODAY(),-7)) | D31: =SUMIFS(Transactions!$E:$E,Transactions!$D:$D,"Expense",Transactions!$A:$A,">="&(EOMONTH(TODAY(),-8)+1),Transactions!$A:$A,"<="&EOMONTH(TODAY(),-7)) | E31: =$C31-$D31
B32: =TEXT(EOMONTH(TODAY(),-6),"mmm yy") | C32: =SUMIFS(Transactions!$E:$E,Transactions!$D:$D,"Income",Transactions!$A:$A,">="&(EOMONTH(TODAY(),-7)+1),Transactions!$A:$A,"<="&EOMONTH(TODAY(),-6)) | D32: =SUMIFS(Transactions!$E:$E,Transactions!$D:$D,"Expense",Transactions!$A:$A,">="&(EOMONTH(TODAY(),-7)+1),Transactions!$A:$A,"<="&EOMONTH(TODAY(),-6)) | E32: =$C32-$D32
B33: =TEXT(EOMONTH(TODAY(),-5),"mmm yy") | C33: =SUMIFS(Transactions!$E:$E,Transactions!$D:$D,"Income",Transactions!$A:$A,">="&(EOMONTH(TODAY(),-6)+1),Transactions!$A:$A,"<="&EOMONTH(TODAY(),-5)) | D33: =SUMIFS(Transactions!$E:$E,Transactions!$D:$D,"Expense",Transactions!$A:$A,">="&(EOMONTH(TODAY(),-6)+1),Transactions!$A:$A,"<="&EOMONTH(TODAY(),-5)) | E33: =$C33-$D33
B34: =TEXT(EOMONTH(TODAY(),-4),"mmm yy") | C34: =SUMIFS(Transactions!$E:$E,Transactions!$D:$D,"Income",Transactions!$A:$A,">="&(EOMONTH(TODAY(),-5)+1),Transactions!$A:$A,"<="&EOMONTH(TODAY(),-4)) | D34: =SUMIFS(Transactions!$E:$E,Transactions!$D:$D,"Expense",Transactions!$A:$A,">="&(EOMONTH(TODAY(),-5)+1),Transactions!$A:$A,"<="&EOMONTH(TODAY(),-4)) | E34: =$C34-$D34
B35: =TEXT(EOMONTH(TODAY(),-3),"mmm yy") | C35: =SUMIFS(Transactions!$E:$E,Transactions!$D:$D,"Income",Transactions!$A:$A,">="&(EOMONTH(TODAY(),-4)+1),Transactions!$A:$A,"<="&EOMONTH(TODAY(),-3)) | D35: =SUMIFS(Transactions!$E:$E,Transactions!$D:$D,"Expense",Transactions!$A:$A,">="&(EOMONTH(TODAY(),-4)+1),Transactions!$A:$A,"<="&EOMONTH(TODAY(),-3)) | E35: =$C35-$D35
B36: =TEXT(EOMONTH(TODAY(),-2),"mmm yy") | C36: =SUMIFS(Transactions!$E:$E,Transactions!$D:$D,"Income",Transactions!$A:$A,">="&(EOMONTH(TODAY(),-3)+1),Transactions!$A:$A,"<="&EOMONTH(TODAY(),-2)) | D36: =SUMIFS(Transactions!$E:$E,Transactions!$D:$D,"Expense",Transactions!$A:$A,">="&(EOMONTH(TODAY(),-3)+1),Transactions!$A:$A,"<="&EOMONTH(TODAY(),-2)) | E36: =$C36-$D36
B37: =TEXT(EOMONTH(TODAY(),-1),"mmm yy") | C37: =SUMIFS(Transactions!$E:$E,Transactions!$D:$D,"Income",Transactions!$A:$A,">="&(EOMONTH(TODAY(),-2)+1),Transactions!$A:$A,"<="&EOMONTH(TODAY(),-1)) | D37: =SUMIFS(Transactions!$E:$E,Transactions!$D:$D,"Expense",Transactions!$A:$A,">="&(EOMONTH(TODAY(),-2)+1),Transactions!$A:$A,"<="&EOMONTH(TODAY(),-1)) | E37: =$C37-$D37
B38: =TEXT(EOMONTH(TODAY(),0),"mmm yy") | C38: =SUMIFS(Transactions!$E:$E,Transactions!$D:$D,"Income",Transactions!$A:$A,">="&(EOMONTH(TODAY(),-1)+1),Transactions!$A:$A,"<="&EOMONTH(TODAY(),0)) | D38: =SUMIFS(Transactions!$E:$E,Transactions!$D:$D,"Expense",Transactions!$A:$A,">="&(EOMONTH(TODAY(),-1)+1),Transactions!$A:$A,"<="&EOMONTH(TODAY(),0)) | E38: =$C38-$D38
B40: 🏷️ Where the Money Goes — Selected Period
B62: Tip: log transactions in the Transactions tab — every number and chart here refreshes on its own.

Sheet Transactions
A1: Date | B1: Description | C1: Category | D1: Type | E1: Amount | F1: Account | G1: Notes
A2: 45870 | B2: Apartment rent | C2: Housing | D2: Expense | E2: 18000 | F2: BPI Checking
A3: 45871 | B3: Anytime Fitness membership | C3: Health & Fitness | D3: Expense | E3: 1500 | F3: Credit Card
A4: 45872 | B4: Netflix | C4: Subscriptions | D4: Expense | E4: 549 | F4: Credit Card
A5: 45872 | B5: Landers grocery haul | C5: Groceries | D5: Expense | E5: 3189 | F5: GCash
A6: 45872 | B6: Landers grocery haul | C6: Groceries | D6: Expense | E6: 2901 | F6: GCash
A7: 45872 | B7: Steam game | C7: Entertainment | D7: Expense | E7: 552 | F7: GCash
A8: 45874 | B8: Monthly salary — payroll | C8: Salary | D8: Income | E8: 72000 | F8: BPI Checking
A9: 45874 | B9: Milk tea run | C9: Dining Out | D9: Expense | E9: 469 | F9: Credit Card
A10: 45876 | B10: Spotify Premium | C10: Subscriptions | D10: Expense | E10: 194 | F10: Credit Card
A11: 45877 | B11: WalterMart groceries | C11: Groceries | D11: Expense | E11: 2830 | F11: Cash
A12: 45877 | B12: Gas — Shell | C12: Transportation | D12: Expense | E12: 648 | F12: GCash
A13: 45878 | B13: iCloud+ storage | C13: Subscriptions | D13: Expense | E13: 99 | F13: Credit Card
... A251: 46215 | B251: Manila Water | C251: Utilities | D251: Expense | E251: 508 | F251: GCash

Sheet Settings
B1: ⚙️ SETTINGS
B2: Categories, budgets, accounts, and the reporting-period engine
B4: CATEGORIES & MONTHLY BUDGETS | F4: ACCOUNTS | H4: REPORTING PERIODS · engine
B5: Edit the yellow cells. Insert rows inside the table to add categories. | F5: Used by the Account dropdown. | H5: Feeds the Dashboard period dropdown — no need to edit.
B6: Category | C6: Type | D6: Monthly Budget | F6: Account | H6: Period | I6: Start | J6: End | K6: Months
B7: Salary | C7: Income | F7: Cash | H7: This Month | I7: =DATE(YEAR(TODAY()),MONTH(TODAY()),1) | J7: =EOMONTH(TODAY(),0) | K7: 1
B8: Freelance | C8: Income | F8: BPI Checking | H8: Last Month | I8: =EOMONTH(TODAY(),-2)+1 | J8: =EOMONTH(TODAY(),-1) | K8: 1
B9: Investment Income | C9: Income | F9: BDO Savings | H9: YTD (This Year) | I9: =DATE(YEAR(TODAY()),1,1) | J9: =EOMONTH(TODAY(),0) | K9: =MONTH(TODAY())
B10: Other Income | C10: Income | F10: Credit Card | H10: Last 12 Months | I10: =EOMONTH(TODAY(),-12)+1 | J10: =EOMONTH(TODAY(),0) | K10: 12
B11: Housing | C11: Expense | D11: 18000 | F11: GCash | H11: Jan 2026 | I11: 46023 | J11: 46053 | K11: 1
B12: Utilities | C12: Expense | D12: 4500 | F12: Maya | H12: Feb 2026 | I12: 46054 | J12: 46081 | K12: 1
B13: Groceries | C13: Expense | D13: 9000 | H13: Mar 2026 | I13: 46082 | J13: 46112 | K13: 1
B14: Transportation | C14: Expense | D14: 3000 | H14: Apr 2026 | I14: 46113 | J14: 46142 | K14: 1
B15: Dining Out | C15: Expense | D15: 3500 | H15: May 2026 | I15: 46143 | J15: 46173 | K15: 1
B16: Health & Fitness | C16: Expense | D16: 2500 | H16: Jun 2026 | I16: 46174 | J16: 46203 | K16: 1
B17: Entertainment | C17: Expense | D17: 2000 | H17: Jul 2026 | I17: 46204 | J17: 46234 | K17: 1
B18: Shopping | C18: Expense | D18: 3500 | H18: Aug 2026 | I18: 46235 | J18: 46265 | K18: 1
B19: Subscriptions | C19: Expense | D19: 1500 | H19: Sep 2026 | I19: 46266 | J19: 46295 | K19: 1
B20: Education | C20: Expense | D20: 1500 | H20: Oct 2026 | I20: 46296 | J20: 46326 | K20: 1
B21: Miscellaneous | C21: Expense | D21: 1500 | H21: Nov 2026 | I21: 46327 | J21: 46356 | K21: 1
H22: Dec 2026 | I22: 46357 | J22: 46387 | K22: 1
B23: Budgets are sample values — replace them with your own. | H23: Jan 2027 | I23: 46388 | J23: 46418 | K23: 1
H24: Feb 2027 | I24: 46419 | J24: 46446 | K24: 1
H25: Mar 2027 | I25: 46447 | J25: 46477 | K25: 1
H26: Apr 2027 | I26: 46478 | J26: 46507 | K26: 1
H27: May 2027 | I27: 46508 | J27: 46538 | K27: 1
H28: Jun 2027 | I28: 46539 | J28: 46568 | K28: 1
H29: Jul 2027 | I29: 46569 | J29: 46599 | K29: 1
H30: Aug 2027 | I30: 46600 | J30: 46630 | K30: 1
H31: Sep 2027 | I31: 46631 | J31: 46660 | K31: 1
H32: Oct 2027 | I32: 46661 | J32: 46691 | K32: 1
H33: Nov 2027 | I33: 46692 | J33: 46721 | K33: 1
H34: Dec 2027 | I34: 46722 | J34: 46752 | K34: 1

Sheet README
B1: 📖 HOW THIS TRACKER WORKS
B2: 60-second guide
B5: 🚀 QUICK START
B6: 1. Open the Transactions tab and log each transaction on its own row (date, description, category, type, amount, account).
B7: 2. Amounts are always POSITIVE numbers — the Type column (Income / Expense) decides the direction.
B8: 3. Category, Type, and Account are dropdowns. Manage the lists in the Settings tab.
B9: 4. Open the Dashboard and pick a period (This Month, Last Month, YTD, Last 12 Months, or any specific month).
B10: 5. That's it — every KPI, table, and chart recalculates automatically. No refresh button, no macros.
B12: ⚙️ HOW THE AUTOMATION WORKS
B13: • Transactions is the ONLY place raw data lives. The Dashboard is 100% formula-driven — never type numbers there.
B14: • SUMIFS pulls totals by Type, Category, and the date window chosen in the period dropdown.
B15: • INDEX + MATCH converts your dropdown choice into start/end dates using the period engine in Settings.
... B35: Built to be fully automated: log it once in Transactions, read it forever on the Dashboard. 💜
